wida_utils/__init__.py
wida_utils/rosters.py
wf_wida_utils-1.1.0.dist-info/LICENSE
wf_wida_utils-1.1.0.dist-info/METADATA
wf_wida_utils-1.1.0.dist-info/WHEEL
wf_wida_utils-1.1.0.dist-info/top_level.txt
wf_wida_utils-1.1.0.dist-info/RECORD
